show_meetings/__init__.py
show_meetings/cli.py
show_meetings-0.1.0.dist-info/entry_points.txt
show_meetings-0.1.0.dist-info/WHEEL
show_meetings-0.1.0.dist-info/METADATA
show_meetings-0.1.0.dist-info/RECORD
